commands/__init__.py
commands/alias.py
commands/aliases.py
commands/delalias.py
commands/delsound.py
commands/get.py
commands/gplay.py
commands/greeting.py
commands/groupadd.py
commands/groupdel.py
commands/groups.py
commands/history.py
commands/ping.py
commands/rl.py
commands/s.py
commands/sounds.py
commands/stopall.py
commands/yt.py
threebot_codeandkey-0.2.1.data/scripts/threebot.py
threebot_codeandkey-0.2.1.dist-info/LICENSE
threebot_codeandkey-0.2.1.dist-info/METADATA
threebot_codeandkey-0.2.1.dist-info/WHEEL
threebot_codeandkey-0.2.1.dist-info/top_level.txt
threebot_codeandkey-0.2.1.dist-info/RECORD
