Metadata-Version: 2.1
Name: threebot-codeandkey
Version: 0.2.1
Summary: A modular mumble bot
Home-page: https://github.com/codeandkey/threebot
Author: Justin Stanley
Author-email: jtst@iastate.edu
License: UNKNOWN
Project-URL: Bug Tracker, https://github.com/codeandkey/threebot/issues
Platform: UNKNOWN
Classifier: Programming Language :: Python :: 3
Classifier: License :: OSI Approved :: MIT License
Classifier: Operating System :: OS Independent
Requires-Python: >=3.6
License-File: LICENSE
Requires-Dist: pyaudio
Requires-Dist: pymumble
